monasca_events_transform-0.0.5.dist-info/METADATA
monasca_events_transform-0.0.5.dist-info/entry_points.txt
monasca_events_transform-0.0.5.dist-info/RECORD
monasca_events_transform-0.0.5.dist-info/pbr.json
monasca_events_transform-0.0.5.dist-info/metadata.json
monasca_events_transform-0.0.5.dist-info/DESCRIPTION.rst
monasca_events_transform-0.0.5.dist-info/WHEEL
monasca_events_transform-0.0.5.dist-info/top_level.txt
monasca_events_transform/database.py
monasca_events_transform/main.py
monasca_events_transform/transform.py
monasca_events_transform/__init__.py
