Metadata-Version: 2.0
Name: monasca-events-transform
Version: 0.0.5
Summary: Monasca event transformation
Home-page: https://github.com/hpcloud-mon/monasca-events-transform
Author: Hewlett-Packard
Author-email: UNKNOWN
License: UNKNOWN
Platform: UNKNOWN
Classifier: Intended Audience :: Information Technology
Classifier: Intended Audience :: System Administrators
Classifier: License :: OSI Approved :: Apache Software License
Classifier: Operating System :: POSIX :: Linux
Classifier: Programming Language :: Python
Classifier: Programming Language :: Python :: 2.7
Requires-Dist: kafka-python (==0.9.2)
Requires-Dist: monasca-statsd
Requires-Dist: PyYAML
Requires-Dist: pbr (>=0.6,<1.0)
Requires-Dist: stackdistiller
Requires-Dist: notigen
